pyspotlightarchiver/__init__.py
pyspotlightarchiver/main.py
pyspotlightarchiver/helpers/__init__.py
pyspotlightarchiver/helpers/download_db.py
pyspotlightarchiver/helpers/download_helper.py
pyspotlightarchiver/helpers/imagehash_helper.py
pyspotlightarchiver/helpers/report_duplicates_helper.py
pyspotlightarchiver/helpers/retry_helper.py
pyspotlightarchiver/helpers/v3_helper.py
pyspotlightarchiver/helpers/v4_helper.py
pyspotlightarchiver/tests/url.txt
pyspotlightarchiver/tests/v3_api.json
pyspotlightarchiver/tests/v4_api.json
pyspotlightarchiver/utils/__init__.py
pyspotlightarchiver/utils/countdown.py
pyspotlightarchiver/utils/download_utils.py
pyspotlightarchiver/utils/exclude_locale.py
pyspotlightarchiver/utils/exif_utils.py
pyspotlightarchiver/utils/list_url.py
pyspotlightarchiver/utils/locale_data.py
pyspotlightarchiver-1.1.2.dist-info/METADATA
pyspotlightarchiver-1.1.2.dist-info/WHEEL
pyspotlightarchiver-1.1.2.dist-info/entry_points.txt
pyspotlightarchiver-1.1.2.dist-info/licenses/LICENSE
pyspotlightarchiver-1.1.2.dist-info/RECORD
