Metadata-Version: 2.4
Name: pyspotlightarchiver
Version: 1.1.2
Summary: Fetch and download Windows Spotlight images automatically. Lightweight and easy to use.
Project-URL: Homepage, https://github.com/yell0wsuit/pyspotlightarchiver
Project-URL: Issues, https://github.com/yell0wsuit/pyspotlightarchiver/issues
Author: yell0wsuit
License-Expression: GPL-3.0-or-later
License-File: LICENSE
Classifier: Operating System :: OS Independent
Classifier: Programming Language :: Python :: 3
Requires-Python: >=3.10
Requires-Dist: babel
Requires-Dist: imagededup
Requires-Dist: requests
Requires-Dist: rich
